itemlist/__init__.py
itemlist/apps.py
itemlist/docs/example-another-filter-popup.png
itemlist/docs/example-filter-popup.png
itemlist/docs/example-list.png
itemlist/docs/example-search-sort.png
itemlist/filters.py
itemlist/templates/itemlist/embed_list.html
itemlist/templates/itemlist/filters.html
itemlist/templates/itemlist/item_list.html
itemlist/templates/itemlist/list.html
itemlist/templates/itemlist/pagination.html
itemlist/templates/itemlist/row.html
itemlist/templatetags/__init__.py
itemlist/templatetags/itemlist.py
itemlist/views.py
django_itemlist-2026.1.7.dist-info/METADATA
django_itemlist-2026.1.7.dist-info/WHEEL
django_itemlist-2026.1.7.dist-info/licenses/LICENSE
django_itemlist-2026.1.7.dist-info/RECORD
