Metadata-Version: 2.4
Name: django-itemlist
Version: 2026.1.7
Summary: A customizable Django Admin ChangeList-like app for use outside of the admin.
License-Expression: MIT
License-File: LICENSE
Author: Michel Fodje
Author-email: michel4j@gmail.com
Requires-Python: >=3.12
Classifier: Environment :: Web Environment
Classifier: Framework :: Django
Classifier: Intended Audience :: Developers
Classifier: License :: OSI Approved :: MIT License
Classifier: Operating System :: OS Independent
Classifier: Programming Language :: Python
Classifier: Topic :: Internet :: WWW/HTTP
Classifier: Topic :: Internet :: WWW/HTTP :: Dynamic Content
Classifier: Topic :: Software Development :: Libraries :: Application Frameworks
Classifier: Topic :: Software Development :: Libraries :: Python Modules
Requires-Dist: django (>=5.2.11,<7.0.0)
Project-URL: Homepage, https://github.com/michel4j/django-itemlist
Project-URL: Issues, https://github.com/michel4j/django-itemlist/issues
